lovelang.py
lovelang-0.1.0.dist-info/licenses/LICENSE
lovelang-0.1.0.dist-info/METADATA
lovelang-0.1.0.dist-info/WHEEL
lovelang-0.1.0.dist-info/entry_points.txt
lovelang-0.1.0.dist-info/top_level.txt
lovelang-0.1.0.dist-info/RECORD
