Metadata-Version: 2.4
Name: lovelang
Version: 0.1.0
Summary: LoveLang - A Hinglish-based programming language
Home-page: https://github.com/CodeGoura/lovelang
Author: Gourahari
Author-email: Gourahari <codegoura+lovelang@gmail.com>
License: MIT
Requires-Python: >=3.8
License-File: LICENSE
Dynamic: author
Dynamic: home-page
Dynamic: license-file
Dynamic: requires-python
